[{"Body":{"ClassId":"workflow.CustomDataTypeDefinition","Description":"NetApp storage target device.","Label":"NetApp Storage Target Datatype","Name":"NetAppStorageTargetDataType","ObjectType":"workflow.CustomDataTypeDefinition","ParameterSet":[],"Properties":{"ObjectType":"workflow.CustomDataTypeProperties"},"SharedScope":"shared","TypeDefinition":[{"CustomDataTypeProperties":{"ObjectType":"workflow.CustomDataProperty"},"Default":{"ObjectType":"workflow.DefaultValue"},"Description":"Storage target device.","DisplayMeta":{"InventorySelector":true,"ObjectType":"workflow.DisplayMeta","WidgetType":"None"},"Label":"Storage Device","Name":"StorageDevice","ObjectType":"workflow.TargetDataType","Properties":[{"ConnectorAttribute":"RegisteredDevice.Moid","ConstraintAttributes":["ObjectType"],"DisplayAttributes":["Name","ManagementAddress"],"ObjectType":"workflow.TargetProperty","Selector":"/api/v1/storage/NetAppClusters?$orderby=Name","SelectorProperty":{"Method":"GET","ObjectType":"workflow.SelectorProperty"},"SupportedObjects":["storage.NetAppCluster"]}],"Required":true}]},"ClassId":"bulk.RestSubRequest","ObjectType":"bulk.RestSubRequest","TargetMoid":"","Uri":"/v1/workflow/CustomDataTypeDefinitions","Verb":"POST"},{"Body":{"ClassId":"workflow.CustomDataTypeDefinition","Description":"NetApp storage virtual machine name.","Label":"NetApp Storage Virtual Machine","Name":"NetAppStorageVirtualMachineNameType","ObjectType":"workflow.CustomDataTypeDefinition","ParameterSet":[],"Properties":{"ObjectType":"workflow.CustomDataTypeProperties"},"SharedScope":"shared","TypeDefinition":[{"Default":{"ObjectType":"workflow.DefaultValue"},"DisplayMeta":{"InventorySelector":true,"ObjectType":"workflow.DisplayMeta","WidgetType":"None"},"Label":"Storage Virtual Machine","Name":"StorageVirtualMachineName","ObjectType":"workflow.PrimitiveDataType","Properties":{"Constraints":{"EnumList":[],"Max":47,"Min":1,"ObjectType":"workflow.Constraints","Regex":"[0-9A-z_][-A-z0-9._]*"},"InventorySelector":[{"DisplayAttributes":["Name"],"ObjectType":"workflow.MoReferenceProperty","Selector":"/api/v1/storage/NetAppStorageVms?$orderby=Name&$select=Name","SelectorProperty":{"Method":"GET","ObjectType":"workflow.SelectorProperty"},"ValueAttribute":"Name"}],"ObjectType":"workflow.PrimitiveDataProperty","Type":"string"},"Required":true}]},"ClassId":"bulk.RestSubRequest","ObjectType":"bulk.RestSubRequest","TargetMoid":"","Uri":"/v1/workflow/CustomDataTypeDefinitions","Verb":"POST"},{"Body":{"ClassId":"workflow.TaskDefinition","DefaultVersion":true,"Description":"Remove initiator from an initiator group with storage virtual machine name, initiator group name, and an initiator to be removed as the inputs. On successful execution, the initiator group name and list of remaining initiators (if any) are generated as outputs.","Label":"Remove Initiator from NetApp Initiator Group","Name":"RemoveInitiatorFromNetAppInitiatorGroup","ObjectType":"workflow.TaskDefinition","Properties":{"InputDefinition":[{"CustomDataTypeProperties":{"CatalogMoid":"shared","CustomDataTypeName":"NetAppStorageTargetDataType","ObjectType":"workflow.CustomDataProperty"},"Default":{"ObjectType":"workflow.DefaultValue"},"DisplayMeta":{"InventorySelector":true,"ObjectType":"workflow.DisplayMeta","WidgetType":"None"},"Label":"Storage Device","Name":"StorageDevice","ObjectType":"workflow.TargetDataType","Properties":[],"Required":true},{"Default":{"ObjectType":"workflow.DefaultValue"},"Description":"Storage virtual machine name.","DisplayMeta":{"InventorySelector":true,"ObjectType":"workflow.DisplayMeta","WidgetType":"None"},"Label":"Storage Virtual Machine","Name":"StorageVirtualMachineName","ObjectType":"workflow.CustomDataType","Properties":{"CatalogMoid":"shared","CustomDataTypeName":"NetAppStorageVirtualMachineNameType","ObjectType":"workflow.CustomDataProperty"},"Required":true},{"Default":{"ObjectType":"workflow.DefaultValue"},"Description":"Initiator group name.","DisplayMeta":{"InventorySelector":true,"ObjectType":"workflow.DisplayMeta","WidgetType":"None"},"Label":"Initiator Group","Name":"InitiatorGroupName","ObjectType":"workflow.PrimitiveDataType","Properties":{"Constraints":{"EnumList":[],"Max":96,"Min":1,"ObjectType":"workflow.Constraints"},"InventorySelector":[{"DisplayAttributes":["Name"],"ObjectType":"workflow.MoReferenceProperty","Selector":"/api/v1/storage/NetAppInitiatorGroups?$orderby=Name","SelectorProperty":{"Method":"GET","ObjectType":"workflow.SelectorProperty"},"ValueAttribute":"Name"}],"ObjectType":"workflow.PrimitiveDataProperty","Type":"string"},"Required":true},{"Default":{"ObjectType":"workflow.DefaultValue"},"Description":"Initiator to remove from the initiator group. An example of a valid FC WWPN is \"01:02:03:04:0a:0b:0c:0d\". Examples of valid iSCSI names are \"iqn.1995-08.com.example:string\" and \"eui.0123456789abcdef\".","DisplayMeta":{"InventorySelector":true,"ObjectType":"workflow.DisplayMeta","WidgetType":"None"},"Label":"Initiator","Name":"Initiator","ObjectType":"workflow.PrimitiveDataType","Properties":{"Constraints":{"EnumList":[],"Max":223,"Min":1,"ObjectType":"workflow.Constraints"},"InventorySelector":[],"ObjectType":"workflow.PrimitiveDataProperty","Type":"string"},"Required":true}],"ObjectType":"workflow.Properties","OutputDefinition":[{"Default":{"ObjectType":"workflow.DefaultValue"},"Description":"Initiator group name.","DisplayMeta":{"InventorySelector":true,"ObjectType":"workflow.DisplayMeta","WidgetType":"None"},"Label":"Initiator Group Name","Name":"InitiatorGroupName","ObjectType":"workflow.PrimitiveDataType","Properties":{"Constraints":{"EnumList":[],"Max":96,"Min":1,"ObjectType":"workflow.Constraints"},"InventorySelector":[],"ObjectType":"workflow.PrimitiveDataProperty","Type":"string"},"Required":true},{"ArrayItemType":{"ObjectType":"workflow.PrimitiveArrayItem","Properties":{"Constraints":{"EnumList":[],"ObjectType":"workflow.Constraints"},"InventorySelector":[],"ObjectType":"workflow.PrimitiveDataProperty","Type":"string"}},"Default":{"ObjectType":"workflow.DefaultValue"},"Description":"List of initiators.","DisplayMeta":{"InventorySelector":true,"ObjectType":"workflow.DisplayMeta","WidgetType":"None"},"Label":"Initiators","Max":500,"Min":1,"Name":"InitiatorList","ObjectType":"workflow.ArrayDataType"}],"RetryCount":5,"RetryDelay":10,"RetryPolicy":"Fixed","SupportStatus":"Supported","Timeout":60,"TimeoutPolicy":"Retry"},"RollbackTasks":[],"SharedScope":"shared","Tags":[{"Key":"category","Value":"Storage"},{"Key":"subcategory","Value":"NetApp"},{"Key":"platformType.NetAppActiveIqUnifiedManager","Value":"true"}],"Version":1},"ClassId":"bulk.RestSubRequest","ObjectType":"bulk.RestSubRequest","TargetMoid":"","Uri":"/v1/workflow/TaskDefinitions","Verb":"POST"},{"Body":{"ClassId":"workflow.WorkflowDefinition","DefaultVersion":true,"Description":"Remove initiators from a NetApp initiator group. The Remove Initiator from NetApp Initiator Group task is run in parallel for each initiator provided. The order of completion may differ from the order that the initiators were given.","InputDefinition":[{"CustomDataTypeProperties":{"CatalogMoid":"shared","CustomDataTypeName":"NetAppStorageTargetDataType","ObjectType":"workflow.CustomDataProperty"},"Default":{"ObjectType":"workflow.DefaultValue"},"DisplayMeta":{"InventorySelector":true,"ObjectType":"workflow.DisplayMeta","WidgetType":"None"},"Label":"Storage Device","Name":"StorageDevice","ObjectType":"workflow.TargetDataType","Properties":[],"Required":true},{"Default":{"ObjectType":"workflow.DefaultValue"},"Description":"Storage virtual machine name.","DisplayMeta":{"InventorySelector":true,"ObjectType":"workflow.DisplayMeta","WidgetType":"None"},"Label":"Storage Virtual Machine","Name":"StorageVirtualMachineName","ObjectType":"workflow.CustomDataType","Properties":{"CatalogMoid":"shared","CustomDataTypeName":"NetAppStorageVirtualMachineNameType","ObjectType":"workflow.CustomDataProperty"},"Required":true},{"Default":{"ObjectType":"workflow.DefaultValue"},"Description":"Initiator group name.","DisplayMeta":{"InventorySelector":true,"ObjectType":"workflow.DisplayMeta","WidgetType":"None"},"Label":"Initiator Group","Name":"InitiatorGroupName","ObjectType":"workflow.PrimitiveDataType","Properties":{"Constraints":{"EnumList":[],"Max":96,"Min":1,"ObjectType":"workflow.Constraints"},"InventorySelector":[{"DisplayAttributes":["Name"],"ObjectType":"workflow.MoReferenceProperty","Selector":"/api/v1/storage/NetAppInitiatorGroups?$orderby=Name","SelectorProperty":{"Method":"GET","ObjectType":"workflow.SelectorProperty"},"ValueAttribute":"Name"}],"ObjectType":"workflow.PrimitiveDataProperty","Type":"string"},"Required":true},{"ArrayItemType":{"ObjectType":"workflow.PrimitiveArrayItem","Properties":{"Constraints":{"EnumList":[],"ObjectType":"workflow.Constraints"},"InventorySelector":[],"ObjectType":"workflow.PrimitiveDataProperty","Type":"string"}},"Default":{"ObjectType":"workflow.DefaultValue"},"Description":"Initiators to remove from the initiator group. An example of a valid FC WWPN is \"01:02:03:04:0a:0b:0c:0d\". Examples of valid iSCSI names are \"iqn.1995-08.com.example:string\" and \"eui.0123456789abcdef\".","DisplayMeta":{"InventorySelector":true,"ObjectType":"workflow.DisplayMeta","WidgetType":"None"},"Label":"Initiator","Max":500,"Min":1,"Name":"InitiatorList","ObjectType":"workflow.ArrayDataType","Required":true}],"InputParameterSet":[],"Label":"Remove Initiators from NetApp Initiator Group","Name":"RemoveInitiatorsFromNetAppInitiatorGroup","ObjectType":"workflow.WorkflowDefinition","OutputDefinition":[],"Properties":{"ObjectType":"workflow.WorkflowProperties","SupportStatus":"Supported"},"SharedScope":"user","Tags":[{"Key":"category","Value":"Storage"}],"Tasks":[{"Name":"StartTask","NextTask":"parallelLoop1","ObjectType":"workflow.StartTask"},{"Name":"SuccessEndTask","ObjectType":"workflow.SuccessEndTask"},{"Name":"FailureEndTask","ObjectType":"workflow.FailureEndTask"},{"Count":"{{ len .global.workflow.input.InitiatorList }}","Description":"A Parallel Loop is a control task that runs one task or one sub-workflow multiple times based on a specified count.  The count can be a static value that is specified during design time or a dynamic value that is derived from workflow inputs or task outputs.  When the loop is executed, the count 'N' is determined, N tasks or sub-workflows are scheduled for execution in parallel.  When all N instances of the task or sub-workflow reach a final state the parallel loop will complete and workflow execution will move on to the next task.  If any one of the tasks or sub-workflows fails, then the entire loop will fail.  Dynamic values for count must be specified as a template.  For example, if a loop must run for a count which matches the length of a workflow input called StringArray, then the count must be specified using a template '{{ len .global.workflow.input.StringArray }}'.  The iteration of the loop is available using the keyword '.iteration' and it can be used to control inputs that feed into the task.  For example, the task inside the loop needs to take one value from the workflow input StringArray, then the task string input can be mapped to the template '{{ index .global.workflow.input.StringArray .iteration}}' during design.","Label":"Parallel Loop","LoopStartTask":"RemoveInitiatorFromNetAppInitiatorGroup1","Name":"parallelLoop1","NumberOfBatches":1,"ObjectType":"workflow.LoopTask","OnSuccess":"SuccessEndTask","Parallel":true},{"CatalogMoid":"shared","Description":"Remove initiator from an initiator group with storage virtual machine name, initiator group name, and an initiator to be removed as the inputs. On successful execution, the initiator group name and list of remaining initiators (if any) are generated as outputs.","InputParameters":{"Initiator":"{{ index .global.workflow.input.InitiatorList .iteration}}","InitiatorGroupName":"${workflow.input.InitiatorGroupName}","StorageDevice":"${workflow.input.StorageDevice}","StorageVirtualMachineName":"${workflow.input.StorageVirtualMachineName}"},"Label":"Remove Initiator from NetApp Initiator Group","Name":"RemoveInitiatorFromNetAppInitiatorGroup1","ObjectType":"workflow.WorkerTask","TaskDefinitionName":"RemoveInitiatorFromNetAppInitiatorGroup","Version":1}],"UiInputFilters":[{"Filters":["Ancestors.Moid eq '${StorageDevice.Moid}'"],"Name":"StorageVirtualMachineName","ObjectType":"workflow.UiInputFilter"},{"Filters":["Tenant.Moid eq '${StorageVirtualMachineName.Moid}'"],"Name":"InitiatorGroupName","ObjectType":"workflow.UiInputFilter"}],"UiRenderingData":{"PDModesMeta":{"InitiatorGroupName":"advanced"},"Positions":[{"Name":"StartTask","X":313.45836407379977,"Y":213.10048917409873},{"Name":"SuccessEndTask","X":313.45836407379977,"Y":489.1004891740989},{"Name":"FailureEndTask","X":453.45836407379977,"Y":489.1004891740989},{"Name":"parallelLoop1","X":218.4583640737995,"Y":283.1004891740987},{"Name":"RemoveInitiatorFromNetAppInitiatorGroup1","X":231.4583640737995,"Y":375.1004891740987}]},"VariableDefinition":[],"Version":1},"ClassId":"bulk.RestSubRequest","ObjectType":"bulk.RestSubRequest","TargetMoid":"","Uri":"/v1/workflow/WorkflowDefinitions","Verb":"POST"},{"Body":{"ClassId":"workflow.ErrorResponseHandler","Name":"NetAppApiErrorResponseHandler","ObjectType":"workflow.ErrorResponseHandler","Parameters":[{"AcceptSingleValue":true,"ComplexType":"Error","ItemType":"complex","Name":"Errors","ObjectType":"content.Parameter","Path":"$","Type":"collection"}],"PlatformType":"NetAppActiveIqUnifiedManager","SharedScope":"shared","Types":[{"Name":"Error","ObjectType":"content.ComplexType","Parameters":[{"ItemType":"simple","Name":"Msg","ObjectType":"content.Parameter","Path":"$.error.message","Type":"simple"},{"ItemType":"simple","Name":"ErrorCode","ObjectType":"content.Parameter","Path":"$.error.code","Type":"simple"}]}]},"ClassId":"bulk.RestSubRequest","ObjectType":"bulk.RestSubRequest","TargetMoid":"","Uri":"/v1/workflow/ErrorResponseHandlers","Verb":"POST"},{"Body":{"Batch":[{"ContentType":"json","EndpointRequestType":"Internal","Method":"GET","Name":"GetClusterUuid","ObjectType":"workflow.WebApi","Outcomes":[{"Condition":"{{eq .global.GetClusterUuid.output.HttpStatusCode 200}}","Message":"Get Cluster UUID successful.","ObjectType":"workflow.Outcome","Type":"Success"},{"Condition":"{{ne .global.GetClusterUuid.output.HttpStatusCode 200}}","Message":"Get Cluster UUID failed.","ObjectType":"workflow.Outcome","Type":"Error"}],"Protocol":"https","ResponseSpec":{"ErrorParameters":[],"ObjectType":"content.Grammar","Parameters":[{"AcceptSingleValue":false,"ComplexType":"","ItemType":"simple","Name":"Uuid","ObjectType":"content.Parameter","Path":"$.Uuid","Secure":false,"Type":"simple"}],"Types":[]},"TargetType":"Local","Url":"/v1/storage/NetAppClusters/{{.global.task.input.StorageDevice.Moid}}?$select=Uuid"},{"ContentType":"json","EndpointRequestType":"Internal","Method":"GET","Name":"GetNetAppiGroupUuid","ObjectType":"workflow.WebApi","Outcomes":[{"Condition":"{{ and (ge .global.GetNetAppiGroupUuid.output.HttpStatusCode 400) (le .global.GetNetAppiGroupUuid.output.HttpStatusCode 499)}}","Message":"{{if .global.GetNetAppiGroupUuid.output.Errors}}{{$err := (index .global.GetNetAppiGroupUuid.output.Errors 0)}}{{if (index $err \"Ctx\")}}{{$err.ErrorCode}}: {{end}}{{$err.Msg}}{{else}}{{.global.GetNetAppiGroupUuid.output.HttpStatusMsg}}{{end}}","ObjectType":"workflow.Outcome","Type":"TerminalError"},{"Condition":"{{(eq .global.GetNetAppiGroupUuid.output.HttpStatusCode 500)}}","Message":"{{if .global.GetNetAppiGroupUuid.output.Errors}}{{$err := (index .global.GetNetAppiGroupUuid.output.Errors 0)}}{{if (index $err \"Ctx\")}}{{$err.ErrorCode}}: {{end}}{{$err.Msg}}{{else}}{{.global.GetNetAppiGroupUuid.output.HttpStatusMsg}}{{end}}","ObjectType":"workflow.Outcome","Type":"TerminalError"},{"Condition":"{{ and (ge .global.GetNetAppiGroupUuid.output.HttpStatusCode 501) (le .global.GetNetAppiGroupUuid.output.HttpStatusCode 599)}}","Message":"{{if .global.GetNetAppiGroupUuid.output.Errors}}{{$err := (index .global.GetNetAppiGroupUuid.output.Errors 0)}}{{if (index $err \"Ctx\")}}{{$err.ErrorCode}}: {{end}}{{$err.Msg}}{{else}}{{.global.GetNetAppiGroupUuid.output.HttpStatusMsg}}{{end}}","ObjectType":"workflow.Outcome","Type":"Error"},{"Condition":"{{(eq .global.GetNetAppiGroupUuid.output.HttpStatusCode 200)}}}","Message":"Initiator group details retrieved successfully.","ObjectType":"workflow.Outcome","Type":"Success"}],"Protocol":"https","ResponseSpec":{"ErrorParameters":[],"ObjectType":"content.Grammar","Parameters":[{"AcceptSingleValue":false,"ComplexType":"","ItemType":"simple","Name":"iGroupUuid","ObjectType":"content.Parameter","Path":"$.records[0].uuid","Secure":false,"Type":"simple"}],"Types":[]},"TargetType":"Endpoint","Url":"/api/gateways/{{.global.GetClusterUuid.output.Uuid}}/protocols/san/igroups?name={{.global.task.input.InitiatorGroupName}}&svm.name={{.global.task.input.StorageVirtualMachineName}}"},{"ContentType":"json","EndpointRequestType":"Internal","Method":"DELETE","Name":"RemoveInitiator","ObjectType":"workflow.WebApi","Outcomes":[{"Condition":"{{ and (ge .global.RemoveInitiator.output.HttpStatusCode 400) (le .global.RemoveInitiator.output.HttpStatusCode 499)}}","Message":"{{if .global.RemoveInitiator.output.Errors}}{{$err := (index .global.RemoveInitiator.output.Errors 0)}}{{if (index $err \"Ctx\")}}{{$err.ErrorCode}}: {{end}}{{$err.Msg}}{{else}}{{.global.RemoveInitiator.output.HttpStatusMsg}}{{end}}","ObjectType":"workflow.Outcome","Type":"TerminalError"},{"Condition":"{{(eq .global.RemoveInitiator.output.HttpStatusCode 500)}}","Message":"{{if .global.RemoveInitiator.output.Errors}}{{$err := (index .global.RemoveInitiator.output.Errors 0)}}{{if (index $err \"Ctx\")}}{{$err.ErrorCode}}: {{end}}{{$err.Msg}}{{else}}{{.global.RemoveInitiator.output.HttpStatusMsg}}{{end}}","ObjectType":"workflow.Outcome","Type":"TerminalError"},{"Condition":"{{ and (ge .global.RemoveInitiator.output.HttpStatusCode 501) (le .global.RemoveInitiator.output.HttpStatusCode 599)}}","Message":"{{if .global.RemoveInitiator.output.Errors}}{{$err := (index .global.RemoveInitiator.output.Errors 0)}}{{if (index $err \"Ctx\")}}{{$err.ErrorCode}}: {{end}}{{$err.Msg}}{{else}}{{.global.RemoveInitiator.output.HttpStatusMsg}}{{end}}","ObjectType":"workflow.Outcome","Type":"Error"},{"Condition":"{{(eq .global.RemoveInitiator.output.HttpStatusCode 200)}}","Message":"Initiator removed successfully.","ObjectType":"workflow.Outcome","Type":"Success"}],"Protocol":"https","TargetType":"Endpoint","Url":"/api/gateways/{{.global.GetClusterUuid.output.Uuid}}/protocols/san/igroups/{{.global.GetNetAppiGroupUuid.output.iGroupUuid}}/initiators/{{.global.task.input.Initiator}}?allow_delete_while_mapped=true"},{"ContentType":"json","EndpointRequestType":"Internal","Method":"GET","Name":"GetNetAppiGroupInitiators","ObjectType":"workflow.WebApi","Outcomes":[{"Condition":"{{ and (ge .global.GetNetAppiGroupInitiators.output.HttpStatusCode 400) (le .global.GetNetAppiGroupInitiators.output.HttpStatusCode 499)}}","Message":"{{if .global.GetNetAppiGroupInitiators.output.Errors}}{{$err := (index .global.GetNetAppiGroupInitiators.output.Errors 0)}}{{if (index $err \"Ctx\")}}{{$err.ErrorCode}}: {{end}}{{$err.Msg}}{{else}}{{.global.GetNetAppiGroupInitiators.output.HttpStatusMsg}}{{end}}","ObjectType":"workflow.Outcome","Type":"TerminalError"},{"Condition":"{{(eq .global.GetNetAppiGroupInitiators.output.HttpStatusCode 500)}}","Message":"{{if .global.GetNetAppiGroupInitiators.output.Errors}}{{$err := (index .global.GetNetAppiGroupInitiators.output.Errors 0)}}{{if (index $err \"Ctx\")}}{{$err.ErrorCode}}: {{end}}{{$err.Msg}}{{else}}{{.global.GetNetAppiGroupInitiators.output.HttpStatusMsg}}{{end}}","ObjectType":"workflow.Outcome","Type":"TerminalError"},{"Condition":"{{ and (ge .global.GetNetAppiGroupInitiators.output.HttpStatusCode 501) (le .global.GetNetAppiGroupInitiators.output.HttpStatusCode 599)}}","Message":"{{if .global.GetNetAppiGroupInitiators.output.Errors}}{{$err := (index .global.GetNetAppiGroupInitiators.output.Errors 0)}}{{if (index $err \"Ctx\")}}{{$err.ErrorCode}}: {{end}}{{$err.Msg}}{{else}}{{.global.GetNetAppiGroupInitiators.output.HttpStatusMsg}}{{end}}","ObjectType":"workflow.Outcome","Type":"Error"},{"Condition":"{{(eq .global.GetNetAppiGroupInitiators.output.HttpStatusCode 200)}}}","Message":"Initiator group details retrieved successfully.","ObjectType":"workflow.Outcome","Type":"Success"}],"Protocol":"https","ResponseSpec":{"ErrorParameters":[],"ObjectType":"content.Grammar","Parameters":[{"AcceptSingleValue":false,"ComplexType":"","ItemType":"simple","Name":"Initiators","ObjectType":"content.Parameter","Path":"$.records[0].initiators[*].name","Secure":false,"Type":"collection"}],"Types":[]},"TargetType":"Endpoint","Url":"/api/gateways/{{.global.GetClusterUuid.output.Uuid}}/protocols/san/igroups?name={{.global.task.input.InitiatorGroupName}}&svm.name={{.global.task.input.StorageVirtualMachineName}}&fields=initiators"},{"Body":"{\"Type\":\"storage.NetAppInitiatorGroup\",\"Queries\": [{\"Uuid\": \"{{.global.GetNetAppiGroupUuid.output.iGroupUuid}}\", \"ClusterUuid\":\"{{.global.GetClusterUuid.output.Uuid}}\"}],\"RegisteredDevice\":\"{{.global.task.target.RegisteredDeviceMoid}}\"}","ContentType":"json","EndpointRequestType":"Internal","Method":"POST","Name":"UpdateInventory","ObjectType":"workflow.WebApi","Outcomes":[{"Condition":"{{eq .global.UpdateInventory.output.HttpStatusCode 200}}","Message":"Initiator removed successfully.","ObjectType":"workflow.Outcome","Type":"Success"},{"Condition":"{{ne .global.UpdateInventory.output.HttpStatusCode 200}}","Message":"{{.global.UpdateInventory.output.HttpStatusMsg}}","ObjectType":"workflow.Outcome","Type":"Error"}],"Protocol":"https","TargetType":"Local","Url":"/v1/task/NetAppScopedInventories"}],"CancelAction":[],"ClassId":"workflow.BatchApiExecutor","Constraints":{"ObjectType":"workflow.TaskConstraints","TargetDataType":{"ObjectType":"storage.NetAppCluster"}},"Description":"Remove initiator from an initiator group.","ErrorResponseHandler":{"ObjectType":"workflow.ErrorResponseHandler","Selector":"Name eq \"NetAppApiErrorResponseHandler\""},"Name":"RemoveInitiatorFromNetAppInitiatorGroup","ObjectType":"workflow.BatchApiExecutor","Output":{"InitiatorGroupName":"{{.global.task.input.InitiatorGroupName}}","InitiatorList":"{{.global.GetNetAppiGroupInitiators.output.Initiators| ToJson}}"},"RetryFromFailedApi":true,"SharedScope":"shared","SkipOnCondition":"{{if ne .global.task.input.StorageDevice.ObjectType \"storage.NetAppCluster\"}} true {{end}}","TaskDefinition":{"ObjectType":"workflow.TaskDefinition","Selector":"Name eq \"RemoveInitiatorFromNetAppInitiatorGroup\" and Version eq 1"}},"ClassId":"bulk.RestSubRequest","ObjectType":"bulk.RestSubRequest","TargetMoid":"","Uri":"/v1/workflow/BatchApiExecutors","Verb":"POST"}]